LindenmayerSystem/LSystem.py
LindenmayerSystem/__init__.py
LindenmayerSystem-1.0.0.dist-info/LICENSE
LindenmayerSystem-1.0.0.dist-info/METADATA
LindenmayerSystem-1.0.0.dist-info/WHEEL
LindenmayerSystem-1.0.0.dist-info/top_level.txt
LindenmayerSystem-1.0.0.dist-info/RECORD
