Metadata-Version: 2.1
Name: LindenmayerSystem
Version: 1.0.0
Summary: A pure python module for generating iterations from the L-System or Lindenmayer system.
Home-page: https://github.com/subimal/LSystem
Author: Subimal Deb
Author-email: subimal.deb@gmail.com
License: UNKNOWN
Platform: UNKNOWN
Classifier: Programming Language :: Python :: 3
Classifier: License :: OSI Approved :: GNU Lesser General Public License v3 or later (LGPLv3+)
Classifier: Operating System :: OS Independent
Requires-Python: >=3.6
